biobert_bern/__init__.py
biobert_bern/_modidx.py
biobert_bern/biobertApi.py
biobert_bern/fmf_biobert.py
biobert_bern-0.0.1.dist-info/LICENSE
biobert_bern-0.0.1.dist-info/METADATA
biobert_bern-0.0.1.dist-info/WHEEL
biobert_bern-0.0.1.dist-info/entry_points.txt
biobert_bern-0.0.1.dist-info/top_level.txt
biobert_bern-0.0.1.dist-info/RECORD
