Metadata-Version: 2.1
Name: biobert-bern
Version: 0.0.1
Summary: Use bioBERT via BERN to label biomedical terms in docs
Home-page: https://github.com/daveramseymusic/biobert-bern
Author: daveramseymusic
Author-email: daveramseymusic@gmail.com
License: Apache Software License 2.0
Keywords: nbdev jupyter notebook python
Classifier: Development Status :: 4 - Beta
Classifier: Intended Audience :: Developers
Classifier: Natural Language :: English
Classifier: Programming Language :: Python :: 3.7
Classifier: Programming Language :: Python :: 3.8
Classifier: Programming Language :: Python :: 3.9
Classifier: Programming Language :: Python :: 3.10
Classifier: License :: OSI Approved :: Apache Software License
Requires-Python: >=3.7
License-File: LICENSE
Requires-Dist: fastcore
Requires-Dist: requests
Requires-Dist: seaborn
Requires-Dist: matplotlib
Requires-Dist: fastai
Provides-Extra: dev
